get_nested_value_by_path/__init__.py
get_nested_value_by_path-0.1.1.dist-info/LICENSE
get_nested_value_by_path-0.1.1.dist-info/METADATA
get_nested_value_by_path-0.1.1.dist-info/WHEEL
get_nested_value_by_path-0.1.1.dist-info/top_level.txt
get_nested_value_by_path-0.1.1.dist-info/RECORD
